Lab5/PreLab5-1/src/down_counter.v
module down_counter (
    input clk,
    input rst_n,
    input count_en,
    input push_onepulse,
    output [15:0] led
);

reg [5:0] cnt;

always @(posedge clk or negedge rst_n) begin
    if(!rst_n)begin
        cnt <= 6'd40;
    end
    else begin
        if(count_en)begin
            cnt <= (push_onepulse) ? 6'd40 : ((cnt==0) ? 6'd40 : cnt-1);
        end
        else begin
            cnt <= (push_onepulse) ? 6'd40 : cnt;
        end
    end
end

assign led[15:1] = (cnt == 0) ? 15'h7FFF : 0;
assign led[0] = (cnt == 0) ? 1 : count_en;
    
endmodule

Lab5/PreLab5-1/src/controller.v
`define PAUSE 0
`define COUNT 1

module controller (
    input clk,
    input rst_n,
    input push_onepulse,
    output count_en
);

reg cs, ns;

always @(posedge clk or negedge rst_n) begin
    if(!rst_n)begin
        cs <= `COUNT;
    end
    else begin
        cs <= ns;
    end
end

always @(*) begin
    if(cs == `COUNT)begin
        ns = (push_onepulse) ? `PAUSE : `COUNT;
    end 
    else begin
        ns = (push_onepulse) ? `COUNT : `PAUSE;
    end
end

assign count_en = (cs == `COUNT) ? 1 : 0;
    
endmodule

Lab7/Lab7-2/src/one_pulse.v
module one_pulse (
    input clk,
    input rst_n,
    input push_debounced,
    output reg push_onepulse
);

reg push_debounced_delay;

always @(posedge clk or negedge rst_n) begin
    if(!rst_n)begin
        push_debounced_delay <= 0;
    end
    else begin
        push_debounced_delay <= push_debounced;
    end
end
    
always @(posedge clk or negedge rst_n) begin
    if(!rst_n)begin
        push_onepulse <= 0;
    end
    else begin
        push_onepulse <= push_debounced & ~push_debounced_delay;
    end
end

endmodule

Lab5/Lab5-1/src/debounce.v
module debounce (
    input clk,
    input rst_n,
    input btn,
    output reg push_debounced
);

reg [3:0] push_window;

always @(posedge clk or negedge rst_n) begin
    if(!rst_n)begin
        push_window <= 0;
    end
    else begin
        push_window <= {btn, push_window[3:1]};
    end
end

always @(posedge clk or negedge rst_n) begin
    if(!rst_n)begin
        push_debounced <= 0;
    end
    else begin
        if(push_window == 4'b1111)begin
            push_debounced <= 1;
        end
        else begin
            push_debounced <= 0;
        end
    end
end
    
endmodule

Lab5/PreLab5-1/src/top.v
`include "debounce.v"
`include "one_pulse.v"
`include "controller.v"
`include "down_counter.v"

module top (
    input clk, 
    input rst_n,
    input [1:0] btn,
    output [15:0] led
);

wire count_en;
wire [1:0] push_debounced;
wire [1:0] push_onepulse;

debounce d1(
    .clk(clk),
    .rst_n(rst_n),
    .btn(btn[0]),
    .push_debounced(push_debounced[0])
);

one_pulse p1(
    .clk(clk),
    .rst_n(rst_n),
    .push_debounced(push_debounced[0]),
    .push_onepulse(push_onepulse[0])
);

debounce d2(
    .clk(clk),
    .rst_n(rst_n),
    .btn(btn[1]),
    .push_debounced(push_debounced[1])
);

one_pulse p2(
    .clk(clk),
    .rst_n(rst_n),
    .push_debounced(push_debounced[1]),
    .push_onepulse(push_onepulse[1])
);

controller c1(
    .clk(clk),
    .rst_n(rst_n),
    .push_onepulse(push_onepulse[0]),
    .count_en(count_en)
);

down_counter dc1(
    .clk(clk),
    .rst_n(rst_n),
    .push_onepulse(push_onepulse[1]),
    .count_en(count_en),
    .led(led)
);
    
endmodule

Lab5/PreLab5-1/src/tb_top.v
`timescale 1ns/10ps
`define cycle 10

module tb_top ();

    reg clk, rst_n;
    reg [1:0] btn;
    wire [15:0] led;

    top t1(
        .clk(clk), 
        .rst_n(rst_n),
        .btn(btn),
        .led(led)
    );
    
    always #(`cycle/2) clk = ~clk;

    initial begin
        clk=0; rst_n=0; btn=2'b00;
        #13 rst_n = 1;
        #600 btn = 2'b01;   //pause
        #100 btn = 2'b10;   //reset
        #100 btn = 2'b01;   //start
        #200 btn = 2'b10;   //reset
        #1000 $finish;
    end

    initial begin
        $dumpfile("down_counter.vcd");
        $dumpvars;
    end



endmodule

Lab5/PreLab5-1/src/down_counter.vcd
$date
	Thu Jun 30 11:40:28 2022
$end
$version
	Icarus Verilog
$end
$timescale
	10ps
$end
$scope module tb_top $end
$var wire 16 ! led [15:0] $end
$var reg 2 " btn [1:0] $end
$var reg 1 # clk $end
$var reg 1 $ rst_n $end
$scope module t1 $end
$var wire 2 % btn [1:0] $end
$var wire 1 # clk $end
$var wire 1 $ rst_n $end
$var wire 2 & push_onepulse [1:0] $end
$var wire 2 ' push_debounced [1:0] $end
$var wire 16 ( led [15:0] $end
$var wire 1 ) count_en $end
$scope module c1 $end
$var wire 1 # clk $end
$var wire 1 * push_onepulse $end
$var wire 1 $ rst_n $end
$var wire 1 ) count_en $end
$var reg 1 + cs $end
$var reg 1 , ns $end
$upscope $end
$scope module d1 $end
$var wire 1 - btn $end
$var wire 1 # clk $end
$var wire 1 $ rst_n $end
$var reg 1 . push_debounced $end
$var reg 4 / push_window [3:0] $end
$upscope $end
$scope module d2 $end
$var wire 1 0 btn $end
$var wire 1 # clk $end
$var wire 1 $ rst_n $end
$var reg 1 1 push_debounced $end
$var reg 4 2 push_window [3:0] $end
$upscope $end
$scope module dc1 $end
$var wire 1 # clk $end
$var wire 1 ) count_en $end
$var wire 1 3 push_onepulse $end
$var wire 1 $ rst_n $end
$var wire 16 4 led [15:0] $end
$var reg 6 5 cnt [5:0] $end
$upscope $end
$scope module p1 $end
$var wire 1 # clk $end
$var wire 1 6 push_debounced $end
$var wire 1 $ rst_n $end
$var reg 1 7 push_debounced_delay $end
$var reg 1 8 push_onepulse $end
$upscope $end
$scope module p2 $end
$var wire 1 # clk $end
$var wire 1 9 push_debounced $end
$var wire 1 $ rst_n $end
$var reg 1 : push_debounced_delay $end
$var reg 1 ; push_onepulse $end
$upscope $end
$upscope $end
$upscope $end
$enddefinitions $end
#0
$dumpvars
0;
0:
09
08
07
06
b101000 5
b1 4
03
b0 2
01
00
b0 /
0.
0-
1,
1+
0*
1)
b1 (
b0 '
b0 &
b0 %
0$
0#
b0 "
b1 !
$end
#500
1#
#1000
0#
#1300
1$
#1500
b100111 5
1#
#2000
0#
#2500
b100110 5
1#
#3000
0#
#3500
b100101 5
1#
#4000
0#
#4500
b100100 5
1#
#5000
0#
#5500
b100011 5
1#
#6000
0#
#6500
b100010 5
1#
#7000
0#
#7500
b100001 5
1#
#8000
0#
#8500
b100000 5
1#
#9000
0#
#9500
b11111 5
1#
#10000
0#
#10500
b11110 5
1#
#11000
0#
#11500
b11101 5
1#
#12000
0#
#12500
b11100 5
1#
#13000
0#
#13500
b11011 5
1#
#14000
0#
#14500
b11010 5
1#
#15000
0#
#15500
b11001 5
1#
#16000
0#
#16500
b11000 5
1#
#17000
0#
#17500
b10111 5
1#
#18000
0#
#18500
b10110 5
1#
#19000
0#
#19500
b10101 5
1#
#20000
0#
#20500
b10100 5
1#
#21000
0#
#21500
b10011 5
1#
#22000
0#
#22500
b10010 5
1#
#23000
0#
#23500
b10001 5
1#
#24000
0#
#24500
b10000 5
1#
#25000
0#
#25500
b1111 5
1#
#26000
0#
#26500
b1110 5
1#
#27000
0#
#27500
b1101 5
1#
#28000
0#
#28500
b1100 5
1#
#29000
0#
#29500
b1011 5
1#
#30000
0#
#30500
b1010 5
1#
#31000
0#
#31500
b1001 5
1#
#32000
0#
#32500
b1000 5
1#
#33000
0#
#33500
b111 5
1#
#34000
0#
#34500
b110 5
1#
#35000
0#
#35500
b101 5
1#
#36000
0#
#36500
b100 5
1#
#37000
0#
#37500
b11 5
1#
#38000
0#
#38500
b10 5
1#
#39000
0#
#39500
b1 5
1#
#40000
0#
#40500
b1111111111111111 !
b1111111111111111 (
b1111111111111111 4
b0 5
1#
#41000
0#
#41500
b1 !
b1 (
b1 4
b101000 5
1#
#42000
0#
#42500
b100111 5
1#
#43000
0#
#43500
b100110 5
1#
#44000
0#
#44500
b100101 5
1#
#45000
0#
#45500
b100100 5
1#
#46000
0#
#46500
b100011 5
1#
#47000
0#
#47500
b100010 5
1#
#48000
0#
#48500
b100001 5
1#
#49000
0#
#49500
b100000 5
1#
#50000
0#
#50500
b11111 5
1#
#51000
0#
#51500
b11110 5
1#
#52000
0#
#52500
b11101 5
1#
#53000
0#
#53500
b11100 5
1#
#54000
0#
#54500
b11011 5
1#
#55000
0#
#55500
b11010 5
1#
#56000
0#
#56500
b11001 5
1#
#57000
0#
#57500
b11000 5
1#
#58000
0#
#58500
b10111 5
1#
#59000
0#
#59500
b10110 5
1#
#60000
0#
#60500
b10101 5
1#
#61000
0#
#61300
1-
b1 "
b1 %
#61500
b1000 /
b10100 5
1#
#62000
0#
#62500
b10011 5
b1100 /
1#
#63000
0#
#63500
b1110 /
b10010 5
1#
#64000
0#
#64500
b10001 5
b1111 /
1#
#65000
0#
#65500
16
b1 '
1.
b10000 5
1#
#66000
0#
#66500
0,
1*
b1111 5
b1 &
18
17
1#
#67000
0#
#67500
b0 !
b0 (
b0 4
0)
0*
0,
b0 &
08
0+
b1110 5
1#
#68000
0#
#68500
1#
#69000
0#
#69500
1#
#70000
0#
#70500
1#
#71000
0#
#71300
0-
10
b10 "
b10 %
#71500
b111 /
b1000 2
1#
#72000
0#
#72500
06
b1100 2
b0 '
0.
b11 /
1#
#73000
0#
#73500
b1 /
07
b1110 2
1#
#74000
0#
#74500
b1111 2
b0 /
1#
#75000
0#
#75500
19
b10 '
11
1#
#76000
0#
#76500
13
b10 &
1;
1:
1#
#77000
0#
#77500
03
b0 &
0;
b101000 5
1#
#78000
0#
#78500
1#
#79000
0#
#79500
1#
#80000
0#
#80500
1#
#81000
0#
#81300
1-
00
b1 "
b1 %
#81500
b1000 /
b111 2
1#
#82000
0#
#82500
09
b0 '
01
b11 2
b1100 /
1#
#83000
0#
#83500
b1110 /
b1 2
0:
1#
#84000
0#
#84500
b0 2
b1111 /
1#
#85000
0#
#85500
16
b1 '
1.
1#
#86000
0#
#86500
1,
1*
b1 &
18
17
1#
#87000
0#
#87500
b1 !
b1 (
b1 4
1)
0*
1,
b0 &
08
1+
1#
#88000
0#
#88500
b100111 5
1#
#89000
0#
#89500
b100110 5
1#
#90000
0#
#90500
b100101 5
1#
#91000
0#
#91500
b100100 5
1#
#92000
0#
#92500
b100011 5
1#
#93000
0#
#93500
b100010 5
1#
#94000
0#
#94500
b100001 5
1#
#95000
0#
#95500
b100000 5
1#
#96000
0#
#96500
b11111 5
1#
#97000
0#
#97500
b11110 5
1#
#98000
0#
#98500
b11101 5
1#
#99000
0#
#99500
b11100 5
1#
#100000
0#
#100500
b11011 5
1#
#101000
0#
#101300
0-
10
b10 "
b10 %
#101500
b111 /
b1000 2
b11010 5
1#
#102000
0#
#102500
06
b11001 5
b1100 2
b0 '
0.
b11 /
1#
#103000
0#
#103500
b1 /
07
b1110 2
b11000 5
1#
#104000
0#
#104500
b10111 5
b1111 2
b0 /
1#
#105000
0#
#105500
19
b10 '
11
b10110 5
1#
#106000
0#
#106500
13
b10101 5
b10 &
1;
1:
1#
#107000
0#
#107500
03
b0 &
0;
b101000 5
1#
#108000
0#
#108500
b100111 5
1#
#109000
0#
#109500
b100110 5
1#
#110000
0#
#110500
b100101 5
1#
#111000
0#
#111500
b100100 5
1#
#112000
0#
#112500
b100011 5
1#
#113000
0#
#113500
b100010 5
1#
#114000
0#
#114500
b100001 5
1#
#115000
0#
#115500
b100000 5
1#
#116000
0#
#116500
b11111 5
1#
#117000
0#
#117500
b11110 5
1#
#118000
0#
#118500
b11101 5
1#
#119000
0#
#119500
b11100 5
1#
#120000
0#
#120500
b11011 5
1#
#121000
0#
#121500
b11010 5
1#
#122000
0#
#122500
b11001 5
1#
#123000
0#
#123500
b11000 5
1#
#124000
0#
#124500
b10111 5
1#
#125000
0#
#125500
b10110 5
1#
#126000
0#
#126500
b10101 5
1#
#127000
0#
#127500
b10100 5
1#
#128000
0#
#128500
b10011 5
1#
#129000
0#
#129500
b10010 5
1#
#130000
0#
#130500
b10001 5
1#
#131000
0#
#131500
b10000 5
1#
#132000
0#
#132500
b1111 5
1#
#133000
0#
#133500
b1110 5
1#
#134000
0#
#134500
b1101 5
1#
#135000
0#
#135500
b1100 5
1#
#136000
0#
#136500
b1011 5
1#
#137000
0#
#137500
b1010 5
1#
#138000
0#
#138500
b1001 5
1#
#139000
0#
#139500
b1000 5
1#
#140000
0#
#140500
b111 5
1#
#141000
0#
#141500
b110 5
1#
#142000
0#
#142500
b101 5
1#
#143000
0#
#143500
b100 5
1#
#144000
0#
#144500
b11 5
1#
#145000
0#
#145500
b10 5
1#
#146000
0#
#146500
b1 5
1#
#147000
0#
#147500
b1111111111111111 !
b1111111111111111 (
b1111111111111111 4
b0 5
1#
#148000
0#
#148500
b1 !
b1 (
b1 4
b101000 5
1#
#149000
0#
#149500
b100111 5
1#
#150000
0#
#150500
b100110 5
1#
#151000
0#
#151500
b100101 5
1#
#152000
0#
#152500
b100100 5
1#
#153000
0#
#153500
b100011 5
1#
#154000
0#
#154500
b100010 5
1#
#155000
0#
#155500
b100001 5
1#
#156000
0#
#156500
b100000 5
1#
#157000
0#
#157500
b11111 5
1#
#158000
0#
#158500
b11110 5
1#
#159000
0#
#159500
b11101 5
1#
#160000
0#
#160500
b11100 5
1#
#161000
0#
#161500
b11011 5
1#
#162000
0#
#162500
b11010 5
1#
#163000
0#
#163500
b11001 5
1#
#164000
0#
#164500
b11000 5
1#
#165000
0#
#165500
b10111 5
1#
#166000
0#
#166500
b10110 5
1#
#167000
0#
#167500
b10101 5
1#
#168000
0#
#168500
b10100 5
1#
#169000
0#
#169500
b10011 5
1#
#170000
0#
#170500
b10010 5
1#
#171000
0#
#171500
b10001 5
1#
#172000
0#
#172500
b10000 5
1#
#173000
0#
#173500
b1111 5
1#
#174000
0#
#174500
b1110 5
1#
#175000
0#
#175500
b1101 5
1#
#176000
0#
#176500
b1100 5
1#
#177000
0#
#177500
b1011 5
1#
#178000
0#
#178500
b1010 5
1#
#179000
0#
#179500
b1001 5
1#
#180000
0#
#180500
b1000 5
1#
#181000
0#
#181500
b111 5
1#
#182000
0#
#182500
b110 5
1#
#183000
0#
#183500
b101 5
1#
#184000
0#
#184500
b100 5
1#
#185000
0#
#185500
b11 5
1#
#186000
0#
#186500
b10 5
1#
#187000
0#
#187500
b1 5
1#
#188000
0#
#188500
b1111111111111111 !
b1111111111111111 (
b1111111111111111 4
b0 5
1#
#189000
0#
#189500
b1 !
b1 (
b1 4
b101000 5
1#
#190000
0#
#190500
b100111 5
1#
#191000
0#
#191500
b100110 5
1#
#192000
0#
#192500
b100101 5
1#
#193000
0#
#193500
b100100 5
1#
#194000
0#
#194500
b100011 5
1#
#195000
0#
#195500
b100010 5
1#
#196000
0#
#196500
b100001 5
1#
#197000
0#
#197500
b100000 5
1#
#198000
0#
#198500
b11111 5
1#
#199000
0#
#199500
b11110 5
1#
#200000
0#
#200500
b11101 5
1#
